{
  "schema_version": "helix_ask_quality_baseline_contract/1",
  "generated_at": "2026-02-18T21:09:10.813Z",
  "source_report": "artifacts/helix-ask-sweep.2026-02-18T210910806Z.json",
  "config": "baseline",
  "summary": {
    "config": "baseline",
    "total": 8,
    "ok": 0,
    "hard_fail": 8,
    "clarify_rate": 0,
    "prompt_leak_rate": 0,
    "decorative_citation_rate": 0,
    "avg_duration_ms": 131,
    "p50_duration_ms": 100,
    "p95_duration_ms": 282,
    "avg_quality_score": 0,
    "quality_rate": 0
  },
  "thresholds": {
    "min_ok_rate": 0.8,
    "max_clarify_rate": 0.35,
    "max_prompt_leak_rate": 0,
    "max_decorative_citation_rate": 0.1,
    "min_avg_quality_score": 0.7,
    "min_quality_rate": 0.6
  },
  "evaluation": {
    "ok_rate": 0,
    "status": "fail",
    "failing_thresholds": [
      "min_ok_rate",
      "min_avg_quality_score",
      "min_quality_rate"
    ]
  }
}
