{
  "version": 1,
  "rootId": "telemetry-console-tree",
  "nodes": [
    {
      "id": "telemetry-console-tree",
      "slug": "telemetry-console-tree",
      "title": "Telemetry and Console Tree",
      "excerpt": "Console telemetry capture, storage, and observability hooks.",
      "bodyMD": "This tree maps console telemetry capture, storage, and observability summaries that feed Helix Ask.\n\nMinimal artifact: telemetry dataflow map.",
      "tags": [
        "telemetry",
        "console",
        "observability"
      ],
      "children": [
        "telemetry-console-routing",
        "telemetry-console-storage",
        "telemetry-console-client",
        "telemetry-badges-panels",
        "telemetry-observability",
        "telemetry-casimir",
        "telemetry-tests"
      ],
      "links": [],
      "summary": "Console telemetry capture, storage, and observability hooks.",
      "nodeType": "concept",
      "inputs": [],
      "outputs": [],
      "assumptions": [],
      "validity": {},
      "deterministic": null,
      "tolerance": null,
      "environment": null,
      "dependencies": [],
      "predictability": {
        "status": "partial",
        "missing": [
          "inputs",
          "outputs",
          "assumptions",
          "validity",
          "deterministic",
          "tolerance",
          "environment"
        ]
      },
      "evidence": [
        {
          "type": "doc",
          "path": "docs/knowledge/telemetry-console-tree.json"
        }
      ]
    },
    {
      "id": "telemetry-console-routing",
      "slug": "telemetry-console-routing",
      "title": "Console Telemetry Routes",
      "excerpt": "Telemetry endpoints for console snapshots.",
      "bodyMD": "Console telemetry endpoints (server/routes/agi.plan.ts).\n\nMinimal artifact: console telemetry API map.",
      "tags": [
        "telemetry",
        "routes",
        "api"
      ],
      "children": [],
      "links": [
        {
          "rel": "parent",
          "to": "telemetry-console-tree"
        }
      ],
      "summary": "Telemetry endpoints for console snapshots.",
      "nodeType": "concept",
      "evidence": [
        {
          "type": "code",
          "path": "server/routes/agi.plan.ts"
        }
      ],
      "inputs": [],
      "outputs": [],
      "assumptions": [],
      "validity": {},
      "deterministic": null,
      "tolerance": null,
      "environment": null,
      "dependencies": [],
      "predictability": {
        "status": "partial",
        "missing": [
          "inputs",
          "outputs",
          "assumptions",
          "validity",
          "deterministic",
          "tolerance",
          "environment"
        ]
      }
    },
    {
      "id": "telemetry-console-storage",
      "slug": "telemetry-console-storage",
      "title": "Console Telemetry Storage",
      "excerpt": "Telemetry persistence and snapshot formats.",
      "bodyMD": "Console telemetry storage (server/services/console-telemetry/store.ts, server/services/console-telemetry/persist.ts, server/services/console-telemetry/summarize.ts, server/_generated/console-telemetry.json, shared/desktop.ts).\n\nMinimal artifact: telemetry snapshot schema.",
      "tags": [
        "telemetry",
        "storage",
        "schemas"
      ],
      "children": [],
      "links": [
        {
          "rel": "parent",
          "to": "telemetry-console-tree"
        }
      ],
      "summary": "Telemetry persistence and snapshot formats.",
      "nodeType": "concept",
      "evidence": [
        {
          "type": "code",
          "path": "server/services/console-telemetry/store.ts"
        },
        {
          "type": "code",
          "path": "server/services/console-telemetry/persist.ts"
        },
        {
          "type": "code",
          "path": "server/services/console-telemetry/summarize.ts"
        },
        {
          "type": "code",
          "path": "server/_generated/console-telemetry.js"
        },
        {
          "type": "code",
          "path": "shared/desktop.ts"
        }
      ],
      "inputs": [],
      "outputs": [],
      "assumptions": [],
      "validity": {},
      "deterministic": null,
      "tolerance": null,
      "environment": null,
      "dependencies": [],
      "predictability": {
        "status": "partial",
        "missing": [
          "inputs",
          "outputs",
          "assumptions",
          "validity",
          "deterministic",
          "tolerance",
          "environment"
        ]
      }
    },
    {
      "id": "telemetry-console-client",
      "slug": "telemetry-console-client",
      "title": "Client Telemetry Capture",
      "excerpt": "Panel telemetry capture and push from the desktop UI.",
      "bodyMD": "Client telemetry capture (client/src/lib/agi/consoleTelemetry.ts, client/src/lib/desktop/panelRegistry.ts, client/src/lib/desktop/panelTelemetryBus.ts).\n\nMinimal artifact: client telemetry capture flow.",
      "tags": [
        "telemetry",
        "client",
        "ui"
      ],
      "children": [],
      "links": [
        {
          "rel": "parent",
          "to": "telemetry-console-tree"
        },
        {
          "rel": "see-also",
          "to": "ui-components-tree"
        }
      ],
      "summary": "Panel telemetry capture and push from the desktop UI.",
      "nodeType": "concept",
      "evidence": [
        {
          "type": "code",
          "path": "client/src/lib/agi/consoleTelemetry.ts"
        },
        {
          "type": "code",
          "path": "client/src/lib/desktop/panelRegistry.ts"
        },
        {
          "type": "code",
          "path": "client/src/lib/desktop/panelTelemetryBus.ts"
        }
      ],
      "inputs": [],
      "outputs": [],
      "assumptions": [],
      "validity": {},
      "deterministic": null,
      "tolerance": null,
      "environment": null,
      "dependencies": [],
      "predictability": {
        "status": "partial",
        "missing": [
          "inputs",
          "outputs",
          "assumptions",
          "validity",
          "deterministic",
          "tolerance",
          "environment"
        ]
      }
    },
    {
      "id": "telemetry-badges-panels",
      "slug": "telemetry-badges-panels",
      "title": "Telemetry Badges and Panels",
      "excerpt": "Telemetry summarizers and badge pipelines.",
      "bodyMD": "Telemetry summarizers and panel utilities (server/services/telemetry/badges.ts, server/services/telemetry/panels.ts, server/skills/telemetry.badges.ts, server/skills/telemetry.panels.ts, shared/badge-telemetry.ts, shared/star-telemetry.ts).\n\nMinimal artifact: badge telemetry summary.",
      "tags": [
        "telemetry",
        "badges",
        "panels"
      ],
      "children": [],
      "links": [
        {
          "rel": "parent",
          "to": "telemetry-console-tree"
        },
        {
          "rel": "see-also",
          "to": "skills-tooling-tree"
        }
      ],
      "summary": "Telemetry summarizers and badge pipelines.",
      "nodeType": "concept",
      "evidence": [
        {
          "type": "code",
          "path": "server/services/telemetry/badges.ts"
        },
        {
          "type": "code",
          "path": "server/services/telemetry/panels.ts"
        },
        {
          "type": "code",
          "path": "server/skills/telemetry.badges.ts"
        },
        {
          "type": "code",
          "path": "server/skills/telemetry.panels.ts"
        },
        {
          "type": "code",
          "path": "shared/badge-telemetry.ts"
        },
        {
          "type": "code",
          "path": "shared/star-telemetry.ts"
        }
      ],
      "inputs": [],
      "outputs": [],
      "assumptions": [],
      "validity": {},
      "deterministic": null,
      "tolerance": null,
      "environment": null,
      "dependencies": [],
      "predictability": {
        "status": "partial",
        "missing": [
          "inputs",
          "outputs",
          "assumptions",
          "validity",
          "deterministic",
          "tolerance",
          "environment"
        ]
      }
    },
    {
      "id": "telemetry-observability",
      "slug": "telemetry-observability",
      "title": "Observability Core",
      "excerpt": "Telemetry adapters and observability stores.",
      "bodyMD": "Observability services (server/services/observability/*, server/services/observability/constraint-pack-telemetry.ts, server/services/observability/tool-event-adapters.ts).\n\nMinimal artifact: observability store map.",
      "tags": [
        "telemetry",
        "observability",
        "stores"
      ],
      "children": [],
      "links": [
        {
          "rel": "parent",
          "to": "telemetry-console-tree"
        }
      ],
      "summary": "Telemetry adapters and observability stores.",
      "nodeType": "concept",
      "evidence": [
        {
          "type": "code",
          "path": "server/services/observability/constraint-pack-telemetry.ts"
        },
        {
          "type": "code",
          "path": "server/services/observability/tool-event-adapters.ts"
        }
      ],
      "inputs": [],
      "outputs": [],
      "assumptions": [],
      "validity": {},
      "deterministic": null,
      "tolerance": null,
      "environment": null,
      "dependencies": [],
      "predictability": {
        "status": "partial",
        "missing": [
          "inputs",
          "outputs",
          "assumptions",
          "validity",
          "deterministic",
          "tolerance",
          "environment"
        ]
      }
    },
    {
      "id": "telemetry-casimir",
      "slug": "telemetry-casimir",
      "title": "Casimir Telemetry",
      "excerpt": "Casimir telemetry ingestion and persistence.",
      "bodyMD": "Casimir telemetry integration (server/services/casimir/telemetry.ts, server/services/casimir/__tests__/casimir-telemetry.spec.ts).\n\nMinimal artifact: Casimir telemetry summary.",
      "tags": [
        "telemetry",
        "casimir",
        "physics"
      ],
      "children": [],
      "links": [
        {
          "rel": "parent",
          "to": "telemetry-console-tree"
        },
        {
          "rel": "see-also",
          "to": "casimir-tiles-tree"
        }
      ],
      "summary": "Casimir telemetry ingestion and persistence.",
      "nodeType": "concept",
      "evidence": [
        {
          "type": "code",
          "path": "server/services/casimir/telemetry.ts"
        },
        {
          "type": "code",
          "path": "server/services/casimir/__tests__/casimir-telemetry.spec.ts"
        }
      ],
      "inputs": [],
      "outputs": [],
      "assumptions": [],
      "validity": {},
      "deterministic": null,
      "tolerance": null,
      "environment": null,
      "dependencies": [],
      "predictability": {
        "status": "partial",
        "missing": [
          "inputs",
          "outputs",
          "assumptions",
          "validity",
          "deterministic",
          "tolerance",
          "environment"
        ]
      }
    },
    {
      "id": "telemetry-tests",
      "slug": "telemetry-tests",
      "title": "Telemetry Tests",
      "excerpt": "Telemetry regressions and console summary tests.",
      "bodyMD": "Telemetry tests (tests/console-summary.spec.ts, server/services/casimir/__tests__/casimir-telemetry.spec.ts).\n\nMinimal artifact: telemetry test checklist.",
      "tags": [
        "telemetry",
        "tests",
        "console"
      ],
      "children": [],
      "links": [
        {
          "rel": "parent",
          "to": "telemetry-console-tree"
        }
      ],
      "summary": "Telemetry regressions and console summary tests.",
      "nodeType": "concept",
      "evidence": [
        {
          "type": "test",
          "path": "tests/console-summary.spec.ts"
        },
        {
          "type": "code",
          "path": "server/services/casimir/__tests__/casimir-telemetry.spec.ts"
        }
      ],
      "inputs": [],
      "outputs": [],
      "assumptions": [],
      "validity": {},
      "deterministic": null,
      "tolerance": null,
      "environment": null,
      "dependencies": [],
      "predictability": {
        "status": "partial",
        "missing": [
          "inputs",
          "outputs",
          "assumptions",
          "validity",
          "deterministic",
          "tolerance",
          "environment"
        ]
      }
    }
  ],
  "schema": {
    "name": "helix-ask-dag-node",
    "version": 1
  }
}
